{"ref":"c2195415-5271-4490-8a55-470e1c1e3bc5","content":"{\"version\":1,\"machineId\":\"7e1b3d38-dd49-4471-8a99-ebbdf1f0282a\",\"content\":\"{\\\"my.code-snippets\\\":\\\"{\\\\n\\\\t// Place your GLOBAL snippets here. Each snippet is defined under a snippet name and has a scope, prefix, body and \\\\n\\\\t// description. Add comma separated ids of the languages where the snippet is applicable in the scope field. If scope \\\\n\\\\t// is left empty or omitted, the snippet gets applied to all languages. The prefix is what is \\\\n\\\\t// used to trigger the snippet and the body will be expanded and inserted. Possible variables are: \\\\n\\\\t// $1, $2 for tab stops, $0 for the final cursor position, and ${1:label}, ${2:another} for placeholders. \\\\n\\\\t// Placeholders with the same ids are connected.\\\\n\\\\t// Example:\\\\n\\\\t// \\\\\\\"Print to console\\\\\\\": {\\\\n\\\\t// \\\\t\\\\\\\"scope\\\\\\\": \\\\\\\"javascript,typescript\\\\\\\",\\\\n\\\\t// \\\\t\\\\\\\"prefix\\\\\\\": \\\\\\\"log\\\\\\\",\\\\n\\\\t// \\\\t\\\\\\\"body\\\\\\\": [\\\\n\\\\t// \\\\t\\\\t\\\\\\\"console.log('$1');\\\\\\\",\\\\n\\\\t// \\\\t\\\\t\\\\\\\"$2\\\\\\\"\\\\n\\\\t// \\\\t],\\\\n\\\\t// \\\\t\\\\\\\"description\\\\\\\": \\\\\\\"Log output to console\\\\\\\"\\\\n\\\\t// }\\\\n\\\\t\\\\\\\"Reset CSS styles\\\\\\\": {\\\\n\\\\t\\\\t\\\\\\\"scope\\\\\\\": \\\\\\\"css\\\\\\\",\\\\n\\\\t\\\\t\\\\\\\"prefix\\\\\\\": \\\\\\\"reset\\\\\\\",\\\\n\\\\t\\\\t\\\\\\\"body\\\\\\\": [\\\\n\\\\t\\\\t\\\\t\\\\\\\"html, body, div, span, applet, object, iframe,\\\\\\\",\\\\n\\\\t\\\\t\\\\t\\\\\\\"h1, h2, h3, h4, h5, h6, p, blockquote, pre,\\\\\\\",\\\\n\\\\t\\\\t\\\\t\\\\\\\"a, abbr, acronym, address, big, cite, code,\\\\\\\",\\\\n\\\\t\\\\t\\\\t\\\\\\\"del, dfn, em, img, ins, kbd, q, s, samp,\\\\\\\",\\\\n\\\\t\\\\t\\\\t\\\\\\\"small, strike, strong, sub, sup, tt, var,\\\\\\\",\\\\n\\\\t\\\\t\\\\t\\\\\\\"b, u, i, center,\\\\\\\",\\\\n\\\\t\\\\t\\\\t\\\\\\\"dl, dt, dd, ol, ul, li,\\\\\\\",\\\\n\\\\t\\\\t\\\\t\\\\\\\"fieldset, form, label, legend,\\\\\\\",\\\\n\\\\t\\\\t\\\\t\\\\\\\"table, caption, tbody, tfoot, thead, tr, th, td,\\\\\\\",\\\\n\\\\t\\\\t\\\\t\\\\\\\"article, aside, canvas, details, embed, \\\\\\\",\\\\n\\\\t\\\\t\\\\t\\\\\\\"figure, figcaption, footer, header, hgroup, \\\\\\\",\\\\n\\\\t\\\\t\\\\t\\\\\\\"menu, nav, output, ruby, section, summary,\\\\\\\",\\\\n\\\\t\\\\t\\\\t\\\\\\\"time, mark, audio, video {\\\\\\\",\\\\n\\\\t\\\\t\\\\t\\\\\\\"\\\\tmargin: 0;\\\\\\\",\\\\n\\\\t\\\\t\\\\t\\\\\\\"\\\\tborder: 0;\\\\\\\",\\\\n\\\\t\\\\t\\\\t\\\\\\\"\\\\tpadding: 0;\\\\\\\",\\\\n\\\\t\\\\t\\\\t\\\\\\\"\\\\tfont-size: 100%;\\\\\\\",\\\\n\\\\t\\\\t\\\\t\\\\\\\"\\\\tfont: inherit;\\\\\\\",\\\\n\\\\t\\\\t\\\\t\\\\\\\"\\\\tvertical-align: baseline;\\\\\\\",\\\\n\\\\t\\\\t\\\\t\\\\\\\"}\\\\\\\",\\\\n\\\\t\\\\t\\\\t\\\\\\\"article, aside, details, figcaption, figure, \\\\\\\",\\\\n\\\\t\\\\t\\\\t\\\\\\\"footer, header, hgroup, menu, nav, section {\\\\\\\",\\\\n\\\\t\\\\t\\\\t\\\\\\\"\\\\tdisplay: block;\\\\\\\",\\\\n\\\\t\\\\t\\\\t\\\\\\\"}\\\\\\\",\\\\n\\\\t\\\\t\\\\t\\\\\\\"body {\\\\\\\",\\\\n\\\\t\\\\t\\\\t\\\\\\\"\\\\tline-height: 1;\\\\\\\",\\\\n\\\\t\\\\t\\\\t\\\\\\\"}\\\\\\\",\\\\n\\\\t\\\\t\\\\t\\\\\\\"ol, ul {\\\\\\\",\\\\n\\\\t\\\\t\\\\t\\\\\\\"\\\\tlist-style: none;\\\\\\\",\\\\n\\\\t\\\\t\\\\t\\\\\\\"}\\\\\\\",\\\\n\\\\t\\\\t\\\\t\\\\\\\"blockquote, q {\\\\\\\",\\\\n\\\\t\\\\t\\\\t\\\\\\\"\\\\tquotes: none;\\\\\\\",\\\\n\\\\t\\\\t\\\\t\\\\\\\"}\\\\\\\",\\\\n\\\\t\\\\t\\\\t\\\\\\\"blockquote:before, blockquote:after,\\\\\\\",\\\\n\\\\t\\\\t\\\\t\\\\\\\"q:before, q:after {\\\\\\\",\\\\n\\\\t\\\\t\\\\t\\\\\\\"\\\\tcontent: '';\\\\\\\",\\\\n\\\\t\\\\t\\\\t\\\\\\\"\\\\tcontent: none;\\\\\\\",\\\\n\\\\t\\\\t\\\\t\\\\\\\"}\\\\\\\",\\\\n\\\\t\\\\t\\\\t\\\\\\\"table {\\\\\\\",\\\\n\\\\t\\\\t\\\\t\\\\\\\"\\\\tborder-collapse: collapse;\\\\\\\",\\\\n\\\\t\\\\t\\\\t\\\\\\\"\\\\tborder-spacing: 0;\\\\\\\",\\\\n\\\\t\\\\t\\\\t\\\\\\\"}\\\\\\\"\\\\n\\\\t\\\\t],\\\\n\\\\t\\\\t\\\\\\\"description\\\\\\\": \\\\\\\"Онуление всех стилей\\\\\\\"\\\\n\\\\t}\\\\n}\\\"}\"}"}